seroba
